subscriptions/__init__.py
subscriptions/abstract.py
subscriptions/admin.py
subscriptions/apps.py
subscriptions/conf.py
subscriptions/currency.py
subscriptions/forms.py
subscriptions/models.py
subscriptions/urls.py
subscriptions/views.py
subscriptions/management/commands/_manager.py
subscriptions/management/commands/process_subscriptions.py
subscriptions/migrations/0001_initial.py
subscriptions/migrations/0002_plan_list_addition.py
subscriptions/migrations/0003_update_plan_list_detail.py
subscriptions/migrations/0004_change_recurrence_unit_type_1.py
subscriptions/migrations/0004_change_recurrence_unit_type_2.py
subscriptions/migrations/0005_update_recurrence_unit_default.py
subscriptions/migrations/0006_add_slugs.py
subscriptions/migrations/__init__.py
subscriptions/static/subscriptions/styles.css
subscriptions/templates/subscriptions/base.html
subscriptions/templates/subscriptions/base_developer.html
subscriptions/templates/subscriptions/dashboard.html
subscriptions/templates/subscriptions/plan_create.html
subscriptions/templates/subscriptions/plan_delete.html
subscriptions/templates/subscriptions/plan_list.html
subscriptions/templates/subscriptions/plan_list_create.html
subscriptions/templates/subscriptions/plan_list_delete.html
subscriptions/templates/subscriptions/plan_list_detail_create.html
subscriptions/templates/subscriptions/plan_list_detail_delete.html
subscriptions/templates/subscriptions/plan_list_detail_list.html
subscriptions/templates/subscriptions/plan_list_detail_update.html
subscriptions/templates/subscriptions/plan_list_list.html
subscriptions/templates/subscriptions/plan_list_update.html
subscriptions/templates/subscriptions/plan_update.html
subscriptions/templates/subscriptions/subscribe_cancel.html
subscriptions/templates/subscriptions/subscribe_confirmation.html
subscriptions/templates/subscriptions/subscribe_list.html
subscriptions/templates/subscriptions/subscribe_preview.html
subscriptions/templates/subscriptions/subscribe_thank_you.html
django_flexible_subscriptions-0.15.1.dist-info/COPYING
django_flexible_subscriptions-0.15.1.dist-info/LICENSE
django_flexible_subscriptions-0.15.1.dist-info/METADATA
django_flexible_subscriptions-0.15.1.dist-info/WHEEL
django_flexible_subscriptions-0.15.1.dist-info/top_level.txt
django_flexible_subscriptions-0.15.1.dist-info/RECORD
