Metadata-Version: 2.1
Name: django-flexible-subscriptions
Version: 0.15.1
Summary: A subscription and recurrent billing application for Django.
Home-page: https://github.com/studybuffalo/django-flexible-subscriptions
Author: Joshua Torrance
Author-email: studybuffalo@gmail.com
License: UNKNOWN
Project-URL: Documentation, https://django-flexible-subscriptions.readthedocs.io/en/latest/
Project-URL: Source code, https://github.com/studybuffalo/django-flexible-subscriptions
Project-URL: Issues, https://github.com/studybuffalo/django-flexible-subscriptions/issues
Keywords: Django,subscriptions,recurrent billing
Platform: linux
Platform: windows
Classifier: Development Status :: 4 - Beta
Classifier: Environment :: Web Environment
Classifier: Framework :: Django :: 2.2
Classifier: Framework :: Django :: 3.0
Classifier: Intended Audience :: Developers
Classifier: License :: OSI Approved :: GNU General Public License v3 (GPLv3)
Classifier: Operating System :: Unix
Classifier: Programming Language :: Python :: 3
Classifier: Programming Language :: Python :: 3.5
Classifier: Programming Language :: Python :: 3.6
Classifier: Programming Language :: Python :: 3.7
Classifier: Programming Language :: Python :: 3.8
Classifier: Topic :: Other/Nonlisted Topic
Requires-Python: >=3.5
